README.md
setup.cfg
setup.py
bin/edd
edd.egg-info/PKG-INFO
edd.egg-info/SOURCES.txt
edd.egg-info/dependency_links.txt
edd.egg-info/requires.txt
edd.egg-info/top_level.txt
eddlib/__init__.py
eddlib/default_parameters.conf
eddlib/estimate.py
eddlib/experiment.py
eddlib/load_params.py
eddlib/logit.py
eddlib/read_bam.c
eddlib/read_bam.pyx
eddlib/util.py
eddlib/algorithm/__init__.py
eddlib/algorithm/chrom_max_segments.c
eddlib/algorithm/chrom_max_segments.pyx
eddlib/algorithm/max_segments.py
eddlib/algorithm/monte_carlo.py
eddlib/algorithm/unalignable_regions.py