Metadata-Version: 1.0
Name: edd
Version: 1.1.19
Summary: Enriched domain detector for ChIP-seq data
Home-page: http://github.com/CollasLab/edd
Author: Eivind G. Lund
Author-email: e.g.lund@medisin.uio.no
License: UNKNOWN
Platform: UNKNOWN
